Workbook

Sheet How to use
A1: Allston–Brighton Development Feasibility – Pro Forma (filled with public data)
A3: Question
A4: If a new 150-unit building like Hew at 1515 were built in Brighton today, does it pencil out as all market-rate, and what happens under Boston's current Inclusionary Zoning rules (20% affordable at an average of 60% AMI)? What does the city gain in property tax?
A6: How the workbook is organized
A7: Inputs: every assumption, its value, and where it came from. Column E tags each one as Sourced, Derived (calculated from sourced data), or Assumption.
A8: Pro Forma: market-rate vs. inclusionary scenario side by side.
A9: Sensitivity: yield on cost if rents move up or down.
A10: Demand: Census data on the Allston–Brighton–Fenway area.
A11: Policy: tests how much of the inclusionary gap a property tax abatement closes, and what it costs the city.
A13: Before publishing
A14: Items tagged 'Assumption' are the weakest links (hard cost, soft cost, contingency, efficiency, operating expenses). Improve them if you find better sources, and be ready to explain them in an interview.
A15: The land cost is a 2019 purchase price allocated by unit count, not a current land value.
... A26: • No subsidies, density bonuses, tax relief, or debt are modeled. These are natural next steps.

Sheet Inputs
A1: Inputs
A2: Change any yellow cell and the whole model updates. Sources as of October 2026.
A4: Input | B4: Value | C4: Unit | D4: Source / basis | E4: Type
A5: PROJECT
A6: Total units | B6: 150 | C6: units | D6: Hew at 1515 has 150 apartments (Apartments.com; Maloney Properties) | E6: Sourced
A7: Average unit size | B7: 640 | C7: sq ft | D7: Weighted average of Hew floor plans (studio ~450, 1BR ~670, 2BR ~960 sq ft), using Hew's income-restricted unit mix (10 studios / 11 1BR / 5 2BR) as a proxy for the building's mix | E7: Derived
A8: Building efficiency (rentable ÷ gross) | B8: 0.85 | C8: % | D8: Common rule of thumb for mid-rise apartments | E8: Assumption
A9: COSTS
A10: Land cost | B10: 9400000 | C10: $ | D10: The Davis Cos. paid $15.75M for the 2.1-acre site in 2019 for 151 apartments + 102 condos; allocated 151/253 to the apartment wing ≈ $9.4M. 2019 price, not adjusted | E10: Derived
A11: Hard cost per gross sq ft | B11: 450 | C11: $/gross sq ft | D11: No public Boston-specific figure found. US average ~$350/sq ft in 2023 (multifamily.loans); Boston is a high-cost market; multifamily input costs +7.3% in the 12 months to June 2026 (Associated Builders and Contractors, via CRE Daily) | E11: Assumption
A12: Soft costs (% of hard costs) | B12: 0.25 | C12: % | D12: Design, permits, legal, fees | E12: Assumption
A13: Contingency & financing (% of hard + soft) | B13: 0.1 | C13: % | D13: Construction interest and cost overrun buffer | E13: Assumption
A14: REVENUE
A15: Market rent per unit per month | B15: 3875 | C15: $/month | D15: Hew listed rents Oct 2026: studio $3,100; 1BR $3,840–$4,290; 2BR $4,890–$5,150 (Bentley off-campus housing listing); weighted by the proxy mix above | E15: Derived
A16: Concessions (months free per year, market units) | B16: 1 | C16: months | D16: Hew listings advertise one month free rent, some two months (RentHop, BostonPads) | E16: Sourced
A17: Affordable share of units (inclusionary scenario) | B17: 0.2 | C17: % | D17: Boston Inclusionary Zoning (Article 79), effective Oct 1, 2024: large rental projects provide 20% at an average of 60% AMI, or 18% at an average of 50% AMI | E17: Sourced
A18: Affordable rent per unit per month | B18: 1440 | C18: $/month | D18: City of Boston 2025 maximum affordable rents at 60% AMI: studio $1,266, 1BR $1,484, 2BR $1,680; weighted by the proxy mix | E18: Derived
A19: Other income per unit per month | B19: 70 | C19: $/month | D19: Mandatory monthly fees: Greystar lists Hew's total monthly leasing price at $3,366 vs. base rent $3,296 = $70 | E19: Derived
A20: Vacancy & credit loss | B20: 0.05 | C20: % | D20: Northmarq forecasts Greater Boston vacancy near 5.2% at end-2026; Census shows ~6% of units vacant in the area | E20: Sourced
A21: Operating expenses per unit per year (incl. property tax) | B21: 13500 | C21: $/unit/year | D21: ~$5,500 property tax (Boston average sale price ~$441,500/unit [Yardi Matrix] × $12.40 per $1,000) + ~$8,000 other operating costs | E21: Assumption
A22: VALUATION & CITY TAX
A23: Market cap rate (Boston multifamily) | B23: 0.052 | C23: % | D23: Boston luxury Class A multifamily ~5.18% (Apartment Loan Store, Jul 2026); Boston cap rates ~5.2% (Matthews, Jul 2026). Verify against CBRE H1 2026 Cap Rate Survey | E23: Sourced
A24: Property tax rate per $1,000 of value | B24: 12.4 | C24: $ per $1,000 | D24: City of Boston FY2026 residential tax rate (boston.gov, Assessing) | E24: Sourced
A25: Assessed value as % of stabilized value | B25: 1 | C25: % | D25: Assessed values can differ from market value | E25: Assumption
A26: POLICY
A27: Property tax included in operating expenses, per unit per year | B27: 5500 | C27: $/unit/year | D27: Boston average multifamily sale price ~$441,500/unit (Yardi Matrix) × $12.40 per $1,000; this is the portion of opex an abatement would reduce | E27: Derived
A28: Property tax abatement (average over the term) | B28: 0.75 | C28: % | D28: Boston office-to-residential conversion program: average 75% abatement for up to 29 years (Boston Planning Department) | E28: Sourced

Sheet Pro Forma
A1: Pro Forma – stabilized year
A2: A new 150-unit building like Hew at 1515. All figures annual unless noted.
A4: Line item | B4: Market-rate | C4: Inclusionary (20% at 60% AMI) | D4: Difference
A5: UNITS
A6: Total units | B6: =Inputs!$B$6 -> 150 | C6: =Inputs!$B$6 -> 150
A7: Affordable units | B7: =0 -> 0 | C7: =ROUND(Inputs!$B$6*Inputs!$B$17,0) -> 30 | D7: =C7-B7 -> 30
A8: Market-rate units | B8: =B6-B7 -> 150 | C8: =C6-C7 -> 120 | D8: =C8-B8 -> -30
A9: Rentable sq ft | B9: =Inputs!$B$6*Inputs!$B$7 -> 96000 | C9: =Inputs!$B$6*Inputs!$B$7 -> 96000
A10: Gross building sq ft | B10: =IFERROR(B9/Inputs!$B$8,0) -> 112941.18 | C10: =IFERROR(C9/Inputs!$B$8,0) -> 112941.18
A11: DEVELOPMENT COST ($)
A12: Land | B12: =Inputs!$B$10 -> 9400000 | C12: =Inputs!$B$10 -> 9400000
A13: Hard costs | B13: =B10*Inputs!$B$11 -> 50823529 | C13: =C10*Inputs!$B$11 -> 50823529
A14: Soft costs | B14: =B13*Inputs!$B$12 -> 12705882 | C14: =C13*Inputs!$B$12 -> 12705882
A15: Contingency & financing | B15: =(B13+B14)*Inputs!$B$13 -> 6352941.2 | C15: =(C13+C14)*Inputs!$B$13 -> 6352941.2
A16: Total development cost | B16: =SUM(B12:B15) -> 79282353 | C16: =SUM(C12:C15) -> 79282353
A17: Cost per unit | B17: =IFERROR(B16/B6,0) -> 528549.02 | C17: =IFERROR(C16/C6,0) -> 528549.02
A18: OPERATIONS ($)
A19: Gross potential rent | B19: =(B8*Inputs!$B$15+B7*Inputs!$B$18)*12 -> 6975000 | C19: =(C8*Inputs!$B$15+C7*Inputs!$B$18)*12 -> 6098400 | D19: =C19-B19 -> -876600
A20: Less: concessions (market units) | B20: =-B8*Inputs!$B$15*Inputs!$B$16 -> -581250 | C20: =-C8*Inputs!$B$15*Inputs!$B$16 -> -465000 | D20: =C20-B20 -> 116250
A21: Other income | B21: =B6*Inputs!$B$19*12 -> 126000 | C21: =C6*Inputs!$B$19*12 -> 126000
A22: Less: vacancy & credit loss | B22: =-(B19+B20+B21)*Inputs!$B$20 -> -325987.5 | C22: =-(C19+C20+C21)*Inputs!$B$20 -> -287970 | D22: =C22-B22 -> 38017.5
A23: Effective gross income | B23: =SUM(B19:B22) -> 6193762.5 | C23: =SUM(C19:C22) -> 5471430 | D23: =C23-B23 -> -722332.5
A24: Less: operating expenses | B24: =-B6*Inputs!$B$21 -> -2025000 | C24: =-C6*Inputs!$B$21 -> -2025000
A25: Net operating income (NOI) | B25: =B23+B24 -> 4168762.5 | C25: =C23+C24 -> 3446430 | D25: =C25-B25 -> -722332.5
A26: RETURNS
A27: Yield on cost (NOI ÷ total cost) | B27: =IFERROR(B25/B16,0) -> 0.052581216 | C27: =IFERROR(C25/C16,0) -> 0.043470329 | D27: =C27-B27 -> -0.0091108863
A28: Market cap rate | B28: =Inputs!$B$23 -> 0.052 | C28: =Inputs!$B$23 -> 0.052
A29: Development spread (yield on cost – cap rate) | B29: =B27-B28 -> 0.00058121568 | C29: =C27-C28 -> -0.0085296706 | D29: =C29-B29 -> -0.0091108863
A30: Stabilized value (NOI ÷ cap rate) | B30: =IFERROR(B25/B28,0) -> 80168510 | C30: =IFERROR(C25/C28,0) -> 66277500 | D30: =C30-B30 -> -13891010
A31: Developer profit (value – total cost) | B31: =B30-B16 -> 886156.67 | C31: =C30-C16 -> -13004853 | D31: =C31-B31 -> -13891010
A32: Profit margin on cost | B32: =IFERROR(B31/B16,0) -> 0.011177225 | C32: =IFERROR(C31/C16,0) -> -0.16403213 | D32: =C32-B32 -> -0.17520935
A33: WHAT THE CITY GAINS
A34: Estimated annual property tax | B34: =B30*Inputs!$B$25*Inputs!$B$24/1000 -> 994089.52 | C34: =C30*Inputs!$B$25*Inputs!$B$24/1000 -> 821841 | D34: =C34-B34 -> -172248.52
A35: Affordable homes created | B35: =B7 -> 0 | C35: =C7 -> 30 | D35: =C35-B35 -> 30
A36: Funding gap to break even (if profit < 0) | B36: =MAX(0,-B31) -> 0 | C36: =MAX(0,-C31) -> 13004853 | D36: =C36-B36 -> 13004853
A37: Gap per affordable unit | B37: =0 -> 0 | C37: =IFERROR(C36/C7,0) -> 433495.1
A39: Takeaway
A40: ="As all market-rate, yield on cost is "&TEXT(B27,"0.0%")&" vs. a "&TEXT(B28,"0.0%")&" cap rate. Under Inclusionary Zoning ("&TEXT(C7,"0")&" affordable units), it falls to "&TEXT(C27,"0.0%")&", leaving a gap of about "&TEXT(C36,"$#,##0")&" ("&TEXT(C37,"$#,##0")&" per affordable unit). The building would still pay about "&TEXT(C34,"$#,##0")&" a year in property tax." -> As all market-rate, yield on cost is 5.3% vs. a 5.2% cap rate. Under Inclusionary Zoning (30 affordable units), it falls to 4.3%, leaving a gap of about $13,004,853 ($433,495 per affordable unit). The building would still pay about $821,841 a year in property tax.

Sheet Sensitivity
A1: Sensitivity – yield on cost if market rents move
A2: Market rents (and concessions) move; affordable rents, other income, costs and expenses unchanged.
A4: Market rent change | B4: Market-rate yield on cost | C4: Inclusionary yield on cost | D4: Cap rate
A5: -0.1 | B5: =IFERROR((('Pro Forma'!B8*Inputs!$B$15*(1+$A5)*(12-Inputs!$B$16)+'Pro Forma'!B7*Inputs!$B$18*12+'Pro Forma'!B21)*(1-Inputs!$B$20)+'Pro Forma'!B24)/'Pro Forma'!B16,0) -> 0.044919911 | C5: =IFERROR((('Pro Forma'!C8*Inputs!$B$15*(1+$A5)*(12-Inputs!$B$16)+'Pro Forma'!C7*Inputs!$B$18*12+'Pro Forma'!C21)*(1-Inputs!$B$20)+'Pro Forma'!C24)/'Pro Forma'!C16,0) -> 0.037341286 | D5: =Inputs!$B$23 -> 0.052
A6: -0.05 | B6: =IFERROR((('Pro Forma'!B8*Inputs!$B$15*(1+$A6)*(12-Inputs!$B$16)+'Pro Forma'!B7*Inputs!$B$18*12+'Pro Forma'!B21)*(1-Inputs!$B$20)+'Pro Forma'!B24)/'Pro Forma'!B16,0) -> 0.048750563 | C6: =IFERROR((('Pro Forma'!C8*Inputs!$B$15*(1+$A6)*(12-Inputs!$B$16)+'Pro Forma'!C7*Inputs!$B$18*12+'Pro Forma'!C21)*(1-Inputs!$B$20)+'Pro Forma'!C24)/'Pro Forma'!C16,0) -> 0.040405808 | D6: =Inputs!$B$23 -> 0.052
A7: 0 | B7: =IFERROR((('Pro Forma'!B8*Inputs!$B$15*(1+$A7)*(12-Inputs!$B$16)+'Pro Forma'!B7*Inputs!$B$18*12+'Pro Forma'!B21)*(1-Inputs!$B$20)+'Pro Forma'!B24)/'Pro Forma'!B16,0) -> 0.052581216 | C7: =IFERROR((('Pro Forma'!C8*Inputs!$B$15*(1+$A7)*(12-Inputs!$B$16)+'Pro Forma'!C7*Inputs!$B$18*12+'Pro Forma'!C21)*(1-Inputs!$B$20)+'Pro Forma'!C24)/'Pro Forma'!C16,0) -> 0.043470329 | D7: =Inputs!$B$23 -> 0.052
A8: 0.05 | B8: =IFERROR((('Pro Forma'!B8*Inputs!$B$15*(1+$A8)*(12-Inputs!$B$16)+'Pro Forma'!B7*Inputs!$B$18*12+'Pro Forma'!B21)*(1-Inputs!$B$20)+'Pro Forma'!B24)/'Pro Forma'!B16,0) -> 0.056411868 | C8: =IFERROR((('Pro Forma'!C8*Inputs!$B$15*(1+$A8)*(12-Inputs!$B$16)+'Pro Forma'!C7*Inputs!$B$18*12+'Pro Forma'!C21)*(1-Inputs!$B$20)+'Pro Forma'!C24)/'Pro Forma'!C16,0) -> 0.046534851 | D8: =Inputs!$B$23 -> 0.052
A9: 0.1 | B9: =IFERROR((('Pro Forma'!B8*Inputs!$B$15*(1+$A9)*(12-Inputs!$B$16)+'Pro Forma'!B7*Inputs!$B$18*12+'Pro Forma'!B21)*(1-Inputs!$B$20)+'Pro Forma'!B24)/'Pro Forma'!B16,0) -> 0.06024252 | C9: =IFERROR((('Pro Forma'!C8*Inputs!$B$15*(1+$A9)*(12-Inputs!$B$16)+'Pro Forma'!C7*Inputs!$B$18*12+'Pro Forma'!C21)*(1-Inputs!$B$20)+'Pro Forma'!C24)/'Pro Forma'!C16,0) -> 0.049599373 | D9: =Inputs!$B$23 -> 0.052
A11: Developers usually want yield on cost meaningfully above the cap rate to justify construction risk.

Sheet Policy
A1: Policy – can a tax abatement close the inclusionary gap?
A2: Applies the abatement to the inclusionary scenario. Uses the same building, costs and cap rate as the Pro Forma sheet.
A4: Line item | B4: Inclusionary, no abatement | C4: Inclusionary + abatement | D4: Difference
A5: Property tax in operating expenses | B5: ='Pro Forma'!C6*Inputs!$B$27 -> 825000 | C5: ='Pro Forma'!C6*Inputs!$B$27 -> 825000
A6: Tax saved by abatement | B6: =0 -> 0 | C6: =C5*Inputs!$B$28 -> 618750 | D6: =C6-B6 -> 618750
A7: Net operating income (NOI) | B7: ='Pro Forma'!C25 -> 3446430 | C7: ='Pro Forma'!C25+C6 -> 4065180 | D7: =C7-B7 -> 618750
A8: Total development cost | B8: ='Pro Forma'!C16 -> 79282353 | C8: ='Pro Forma'!C16 -> 79282353
A9: Yield on cost | B9: =IFERROR(B7/B8,0) -> 0.043470329 | C9: =IFERROR(C7/C8,0) -> 0.051274714 | D9: =C9-B9 -> 0.0078043849
A10: Market cap rate | B10: =Inputs!$B$23 -> 0.052 | C10: =Inputs!$B$23 -> 0.052
A11: Stabilized value | B11: =IFERROR(B7/B10,0) -> 66277500 | C11: =IFERROR(C7/C10,0) -> 78176538 | D11: =C11-B11 -> 11899038
A12: Developer profit (value – cost) | B12: =B11-B8 -> -13004853 | C12: =C11-C8 -> -1105814.5 | D12: =C12-B12 -> 11899038
A13: Gap remaining (if profit < 0) | B13: =MAX(0,-B12) -> 13004853 | C13: =MAX(0,-C12) -> 1105814.5 | D13: =C13-B13 -> -11899038
A15: WHAT IT COSTS AND DELIVERS
A16: Share of the gap closed by the abatement | B16: =IFERROR(1-C13/B13,0) -> 0.91496909
A17: Foregone property tax to the city, per year | B17: =C6 -> 618750
A18: Affordable homes created | B18: ='Pro Forma'!C7 -> 30
A19: Foregone tax per affordable home, per year | B19: =IFERROR(C6/B18,0) -> 20625
A20: Abatement needed to fully break even | B20: =IFERROR(MIN(1,B13*B10/B5),0) -> 0.81969982
A22: Abatement sensitivity
A23: Abatement | B23: Yield on cost | C23: Developer profit | D23: Foregone tax per year
A24: 0 | B24: =IFERROR(($B$7+$B$5*A24)/$B$8,0) -> 0.043470329 | C24: =IFERROR(($B$7+$B$5*A24)/$B$10-$B$8,0) -> -13004853 | D24: =$B$5*A24 -> 0
A25: 0.25 | B25: =IFERROR(($B$7+$B$5*A25)/$B$8,0) -> 0.046071791 | C25: =IFERROR(($B$7+$B$5*A25)/$B$10-$B$8,0) -> -9038506.8 | D25: =$B$5*A25 -> 206250
A26: 0.5 | B26: =IFERROR(($B$7+$B$5*A26)/$B$8,0) -> 0.048673253 | C26: =IFERROR(($B$7+$B$5*A26)/$B$10-$B$8,0) -> -5072160.6 | D26: =$B$5*A26 -> 412500
A27: 0.75 | B27: =IFERROR(($B$7+$B$5*A27)/$B$8,0) -> 0.051274714 | C27: =IFERROR(($B$7+$B$5*A27)/$B$10-$B$8,0) -> -1105814.5 | D27: =$B$5*A27 -> 618750
A28: 1 | B28: =IFERROR(($B$7+$B$5*A28)/$B$8,0) -> 0.053876176 | C28: =IFERROR(($B$7+$B$5*A28)/$B$10-$B$8,0) -> 2860531.7 | D28: =$B$5*A28 -> 825000
A30: ="A "&TEXT(Inputs!$B$28,"0%")&" abatement closes about "&TEXT(B16,"0%")&" of the inclusionary gap, costing the city about "&TEXT(B17,"$#,##0")&" a year in foregone property tax, or about "&TEXT(B19,"$#,##0")&" per affordable home per year. Full break-even needs about "&TEXT(B20,"0%")&"." -> A 75% abatement closes about 91% of the inclusionary gap, costing the city about $618,750 a year in foregone property tax, or about $20,625 per affordable home per year. Full break-even needs about 82%.

Sheet Demand
A1: Demand – Census data
A2: Source: U.S. Census Bureau, ACS 2024 1-year estimates (some 5-year as noted), via Census Reporter, 'Boston City--Allston, Brighton & Fenway PUMA, MA'. Many figures have margins of error of 10%+.
A4: Metric | B4: Allston–Brighton–Fenway | C4: Massachusetts | D4: Why it matters
A5: Population | B5: 114374 | D5: Scale of the submarket
A6: Median age | B6: 26.2 | C6: 40.1 | D6: Very young market: students and early-career renters
A7: Share of population aged 20–29 | B7: 0.4 | D7: Core renter age group
A8: Persons per household | B8: 1.9 | C8: 2.4 | D8: Small households point to studios and 1-bedrooms
A9: Renter-occupied share | B9: 0.8 | D9: Overwhelmingly a rental market
A10: Occupied share of housing units | B10: 0.94 | D10: ~6% vacancy; supports the vacancy input
A11: Moved since previous year | B11: 0.315 | C11: 0.108 | D11: High turnover: steady leasing demand, retention matters
A12: Median household income | B12: 80614 | C12: 104828 | D12: Anchor for affordability
A13: Persons below poverty line | B13: 0.203 | C13: 0.097 | D13: Supports the case for affordable units
A14: Commute by public transit | B14: 0.28 | D14: Transit access is a key amenity
A15: Commute by walking | B15: 0.21 | D15: Walkability matters
A16: Median value, owner-occupied units (5-yr) | B16: 649900 | C16: 607400 | D16: Ownership is expensive, keeping households renting
A18: Note: this area includes Fenway, which has many students. For Brighton only, pull the census tracts around Hew on data.census.gov.
